{"errors":[],"warnings":[],"namedChunkGroups":{"polyfill":{"chunks":[3,9],"assets":["webpack-runtime-c8ff900a65b65af0eba6.js","webpack-runtime-c8ff900a65b65af0eba6.js.map","polyfill-7ce8899afcd175e429bd.js","polyfill-7ce8899afcd175e429bd.js.map"],"children":{},"childAssets":{}},"app":{"chunks":[3,2,8,4],"assets":["webpack-runtime-c8ff900a65b65af0eba6.js","webpack-runtime-c8ff900a65b65af0eba6.js.map","styles.4630ac11e08ee5b39450.css","styles-7d4153d260c0197f0043.js","styles-7d4153d260c0197f0043.js.map","framework-8e528b732ab2eaadb7b7.js","framework-8e528b732ab2eaadb7b7.js.map","app-07e2629e4e8d3e125d7a.js","app-07e2629e4e8d3e125d7a.js.map"],"children":{},"childAssets":{}},"component---src-pages-404-js":{"chunks":[0,1,5],"assets":["a9a7754c-cdd4c86d19e0b6a769fa.js","a9a7754c-cdd4c86d19e0b6a769fa.js.map","commons-b7482af9962e787f73e0.js","commons-b7482af9962e787f73e0.js.map","component---src-pages-404-js-e72de98a848d9f330f94.js","component---src-pages-404-js-e72de98a848d9f330f94.js.map"],"children":{},"childAssets":{}},"component---src-pages-blog-js":{"chunks":[0,1,6],"assets":["a9a7754c-cdd4c86d19e0b6a769fa.js","a9a7754c-cdd4c86d19e0b6a769fa.js.map","commons-b7482af9962e787f73e0.js","commons-b7482af9962e787f73e0.js.map","component---src-pages-blog-js-e96710375dd5d13fef4c.js","component---src-pages-blog-js-e96710375dd5d13fef4c.js.map"],"children":{},"childAssets":{}},"component---src-pages-index-js":{"chunks":[2,0,1,7],"assets":["styles.4630ac11e08ee5b39450.css","styles-7d4153d260c0197f0043.js","styles-7d4153d260c0197f0043.js.map","a9a7754c-cdd4c86d19e0b6a769fa.js","a9a7754c-cdd4c86d19e0b6a769fa.js.map","commons-b7482af9962e787f73e0.js","commons-b7482af9962e787f73e0.js.map","component---src-pages-index-js-0a67b62e7e51984119b4.js","component---src-pages-index-js-0a67b62e7e51984119b4.js.map"],"children":{},"childAssets":{}}},"assetsByChunkName":{"polyfill":["webpack-runtime-c8ff900a65b65af0eba6.js","polyfill-7ce8899afcd175e429bd.js"],"app":["webpack-runtime-c8ff900a65b65af0eba6.js","styles.4630ac11e08ee5b39450.css","styles-7d4153d260c0197f0043.js","framework-8e528b732ab2eaadb7b7.js","app-07e2629e4e8d3e125d7a.js"],"component---src-pages-404-js":["a9a7754c-cdd4c86d19e0b6a769fa.js","commons-b7482af9962e787f73e0.js","component---src-pages-404-js-e72de98a848d9f330f94.js"],"component---src-pages-blog-js":["a9a7754c-cdd4c86d19e0b6a769fa.js","commons-b7482af9962e787f73e0.js","component---src-pages-blog-js-e96710375dd5d13fef4c.js"],"component---src-pages-index-js":["styles.4630ac11e08ee5b39450.css","styles-7d4153d260c0197f0043.js","a9a7754c-cdd4c86d19e0b6a769fa.js","commons-b7482af9962e787f73e0.js","component---src-pages-index-js-0a67b62e7e51984119b4.js"]}}